dialite/__init__.py
dialite/_base.py
dialite/_linux.py
dialite/_osx.py
dialite/_windows.py
dialite-0.5.3.dist-info/LICENSE
dialite-0.5.3.dist-info/METADATA
dialite-0.5.3.dist-info/WHEEL
dialite-0.5.3.dist-info/top_level.txt
dialite-0.5.3.dist-info/zip-safe
dialite-0.5.3.dist-info/RECORD
