Metadata-Version: 2.1
Name: dialite
Version: 0.5.3
Summary: Lightweight Python library to show simple dialogs.
Home-page: http://dialite.readthedocs.io
Author: Almar Klein and contributors
Author-email: almar.klein@gmail.com
License: (new) BSD
Download-URL: https://pypi.python.org/pypi/dialite
Keywords: GUI,dialog,lightweight
Platform: any
Classifier: Development Status :: 4 - Beta
Classifier: Intended Audience :: Developers
Classifier: License :: OSI Approved :: BSD License
Classifier: Operating System :: MacOS :: MacOS X
Classifier: Operating System :: Microsoft :: Windows
Classifier: Operating System :: POSIX
Classifier: Programming Language :: Python
Classifier: Programming Language :: Python :: 2.7
Classifier: Programming Language :: Python :: 3.4
Classifier: Programming Language :: Python :: 3.5
Classifier: Programming Language :: Python :: 3.6
Classifier: Programming Language :: Python :: 3.7
Classifier: Programming Language :: Python :: 3.8
Provides: dialite
